erddapy/__init__.py
erddapy/_version.py
erddapy/erddapy.py
erddapy/multiple_server_search.py
erddapy/core/__init__.py
erddapy/core/griddap.py
erddapy/core/interfaces.py
erddapy/core/netcdf.py
erddapy/core/url.py
erddapy/servers/__init__.py
erddapy/servers/erddaps.json
erddapy/servers/servers.py
erddapy-2.2.3.dist-info/LICENSE.txt
erddapy-2.2.3.dist-info/METADATA
erddapy-2.2.3.dist-info/WHEEL
erddapy-2.2.3.dist-info/top_level.txt
erddapy-2.2.3.dist-info/RECORD
