Metadata-Version: 2.1
Name: erddapy
Version: 2.2.3
Summary: Python interface for ERDDAP
Maintainer-email: Alex Kerney <akerney@gmri.org>, Callum Rollo <c.rollo@outlook.com>, Filipe Fernandes <ocefpaf+erddapy@gmail.com>
License: Copyright 2017 Filipe Fernandes
Project-URL: documentation, https://ioos.github.io/erddapy
Project-URL: homepage, https://github.com/ioos/erddapy
Project-URL: repository, https://github.com/ioos/erddapy
Classifier: Programming Language :: Python :: 3 :: Only
Classifier: Programming Language :: Python :: 3.10
Classifier: Programming Language :: Python :: 3.11
Classifier: Programming Language :: Python :: 3.12
Requires-Python: >=3.10
License-File: LICENSE.txt
Requires-Dist: httpx>=0.25.0
Requires-Dist: pandas<3,>=0.25.2
Requires-Dist: pytz
